neural_compressor/common/__init__.py
neural_compressor/common/base_config.py
neural_compressor/common/base_tuning.py
neural_compressor/common/benchmark.py
neural_compressor/common/tuning_param.py
neural_compressor/common/utils/__init__.py
neural_compressor/common/utils/constants.py
neural_compressor/common/utils/logger.py
neural_compressor/common/utils/save_load.py
neural_compressor/common/utils/utility.py
neural_compressor/torch/__init__.py
neural_compressor/torch/algorithms/__init__.py
neural_compressor/torch/algorithms/base_algorithm.py
neural_compressor/torch/algorithms/fp8_quant/__init__.py
neural_compressor/torch/algorithms/fp8_quant/common.py
neural_compressor/torch/algorithms/fp8_quant/fp8_quant.py
neural_compressor/torch/algorithms/fp8_quant/helper_modules.py
neural_compressor/torch/algorithms/fp8_quant/_core/__init__.py
neural_compressor/torch/algorithms/fp8_quant/_core/common.py
neural_compressor/torch/algorithms/fp8_quant/_core/fp_utils.py
neural_compressor/torch/algorithms/fp8_quant/_core/measure.py
neural_compressor/torch/algorithms/fp8_quant/_core/quant_dequant.py
neural_compressor/torch/algorithms/fp8_quant/_core/quantize.py
neural_compressor/torch/algorithms/fp8_quant/_core/scale.py
neural_compressor/torch/algorithms/fp8_quant/_core/utils.py
neural_compressor/torch/algorithms/fp8_quant/_core/scale_methods/__init__.py
neural_compressor/torch/algorithms/fp8_quant/_core/scale_methods/max_abs.py
neural_compressor/torch/algorithms/fp8_quant/_core/scale_methods/smooth_quant.py
neural_compressor/torch/algorithms/fp8_quant/_core/scale_methods/unit_scale.py
neural_compressor/torch/algorithms/fp8_quant/_quant_common/__init__.py
neural_compressor/torch/algorithms/fp8_quant/_quant_common/helper_modules.py
neural_compressor/torch/algorithms/fp8_quant/_quant_common/quant_config.py
neural_compressor/torch/algorithms/fp8_quant/prepare_quant/__init__.py
neural_compressor/torch/algorithms/fp8_quant/prepare_quant/prepare_model.py
neural_compressor_3x_pt-3.0.dist-info/LICENSE
neural_compressor_3x_pt-3.0.dist-info/METADATA
neural_compressor_3x_pt-3.0.dist-info/WHEEL
neural_compressor_3x_pt-3.0.dist-info/entry_points.txt
neural_compressor_3x_pt-3.0.dist-info/third-party-programs.txt
neural_compressor_3x_pt-3.0.dist-info/top_level.txt
neural_compressor_3x_pt-3.0.dist-info/RECORD
